li_easymail/__init__.py
li_easymail/easymail.py
li_easymail-0.1.3.dist-info/LICENSE
li_easymail-0.1.3.dist-info/METADATA
li_easymail-0.1.3.dist-info/WHEEL
li_easymail-0.1.3.dist-info/top_level.txt
li_easymail-0.1.3.dist-info/RECORD
