Metadata-Version: 2.1
Name: li-easymail
Version: 0.1.3
Summary: Simple Gmail API mail sender
Home-page: https://goldstac.github.io/Easymail-Site/
Author: Li Productions
Author-email: none@example.com
License: MIT
Classifier: Programming Language :: Python :: 3
Classifier: License :: OSI Approved :: MIT License
Classifier: Operating System :: OS Independent
Requires-Python: >=3.8
License-File: LICENSE
Requires-Dist: google-auth
Requires-Dist: google-auth-oauthlib
Requires-Dist: google-api-python-client
